pushover/__init__.py
pushover_nythepegasus-1.0.1.dist-info/LICENSE
pushover_nythepegasus-1.0.1.dist-info/METADATA
pushover_nythepegasus-1.0.1.dist-info/WHEEL
pushover_nythepegasus-1.0.1.dist-info/top_level.txt
pushover_nythepegasus-1.0.1.dist-info/RECORD
