Metadata-Version: 2.1
Name: pushover-nythepegasus
Version: 1.0.1
Summary: A simple Pushover client written in Python.
Home-page: UNKNOWN
Author: Nythepegasus
Author-email: nythepegasus84@gmail.com
License: MIT
Project-URL: Source, https://github.com/Nythepegasus/pushover-client/
Project-URL: Tracker, https://github.com/Nythepegasus/pushover-client/issues
Project-URL: Say Thanks!, https://saythanks.io/to/nythepegasus84%40gmail.com
Keywords: pushover,api,client
Platform: UNKNOWN
Classifier: Intended Audience :: Developers
Classifier: Natural Language :: English
Classifier: License :: OSI Approved :: MIT License
Classifier: Programming Language :: Python :: 3 :: Only
Requires-Python: >=3
Requires-Dist: requests
